Metadata-Version: 2.1
Name: rs-simtools
Version: 0.0.1
Summary: RSSimTools
Home-page: https://github.com/RedesignScience/RSSimTools
Author: Gavin Bascom
Author-email: gavin@redesignscience.com
License: UNKNOWN
Platform: UNKNOWN
Classifier: Programming Language :: Python :: 3
Classifier: License :: OSI Approved :: MIT License
Classifier: Operating System :: OS Independent
Requires-Python: >=3.6
